CHANGELOG.txt
LICENCE.txt
MANIFEST.in
README.txt
setup.py
shreyasbasiccalculator/__init__.py
shreyasbasiccalculator.egg-info/PKG-INFO
shreyasbasiccalculator.egg-info/SOURCES.txt
shreyasbasiccalculator.egg-info/dependency_links.txt
shreyasbasiccalculator.egg-info/top_level.txt