Metadata-Version: 1.1
Name: shreyasbasiccalculator
Version: 0.0.1
Summary: A very basic calculator
Home-page: UNKNOWN
Author: shreyas zadge
Author-email: zadgeshreyas@gmail.com
License: MIT
Keywords: calculator
Platform: UNKNOWN
Classifier: Development Status :: 5 - Production/Stable
Classifier: Intended Audience :: Education
Classifier: Operating System :: Unix
Classifier: Operating System :: MacOS :: MacOS X
Classifier: Operating System :: Microsoft :: Windows
Classifier: License :: OSI Approved :: MIT License
Classifier: Programming Language :: Python :: 3
